pydbfi/__init__.py
pydbfi/api.py
pydbfi/main.py
pydbfi/oauth.py
pydbfi/data/__init__.py
pydbfi/data/request.py
pydbfi/data/domestic/__init__.py
pydbfi/data/domestic/request.py
pydbfi/data/overseas/__init__.py
pydbfi/data/overseas/request.py
pydbfi/service/__init__.py
pydbfi/service/chart.py
pydbfi/service/quote.py
pydbfi/service/trading.py
pydbfi/service/common/__init__.py
pydbfi/service/common/base.py
pydbfi/service/common/interfaces.py
pydbfi-0.1.5.dist-info/LICENSE
pydbfi-0.1.5.dist-info/METADATA
pydbfi-0.1.5.dist-info/WHEEL
pydbfi-0.1.5.dist-info/top_level.txt
pydbfi-0.1.5.dist-info/RECORD
