Metadata-Version: 2.2
Name: pydbfi
Version: 0.1.5
Summary: DB증권 API Python SDK
Home-page: https://github.com/leorivk/pydbfi
Author: ivk
Author-email: leorivk@gmail.com
Classifier: Programming Language :: Python :: 3
Classifier: License :: OSI Approved :: MIT License
Classifier: Operating System :: OS Independent
Requires-Python: >=3.6
License-File: LICENSE
Requires-Dist: requests
Dynamic: author
Dynamic: author-email
Dynamic: classifier
Dynamic: description
Dynamic: description-content-type
Dynamic: home-page
Dynamic: requires-dist
Dynamic: requires-python
Dynamic: summary
